README.rst
setup.py
django_simpleapi.egg-info/PKG-INFO
django_simpleapi.egg-info/SOURCES.txt
django_simpleapi.egg-info/dependency_links.txt
django_simpleapi.egg-info/pbr.json
django_simpleapi.egg-info/requires.txt
django_simpleapi.egg-info/top_level.txt
simpleapi/__init__.py
simpleapi/utils.py