Metadata-Version: 1.1
Name: django-simpleapi
Version: 1.4.0
Summary: A Django package that allows you to write APIs simply
Home-page: http://github.com/voidfiles/django-simpleapi
Author: Alex Kessinger
Author-email: voidfiles@gmail.com
License: MIT
Platform: UNKNOWN
Classifier: Development Status :: 5 - Production/Stable
Classifier: Environment :: Web Environment
Classifier: Intended Audience :: Developers
Classifier: License :: OSI Approved :: MIT License
Classifier: Operating System :: OS Independent
Classifier: Programming Language :: Python
Classifier: Framework :: Django
